ka_uts_arr/__init__.py
ka_uts_arr/__version__.py
ka_uts_arr/aoa.py
ka_uts_arr/aoeq.py
ka_uts_arr/aoo.py
ka_uts_arr/aos.py
ka_uts_arr/arr.py
ka_uts_arr/py.typed
ka_uts_arr-4.1.0.250525.dist-info/licenses/LICENSE.txt
ka_uts_arr-4.1.0.250525.dist-info/METADATA
ka_uts_arr-4.1.0.250525.dist-info/WHEEL
ka_uts_arr-4.1.0.250525.dist-info/top_level.txt
ka_uts_arr-4.1.0.250525.dist-info/RECORD
